Workbook

Sheet Pricing
A1: Planes de Membresía — Synapse AI Scanner
A3: Plan | B3: Duración (meses) | C3: Precio Lanzamiento (USD) | D3: Precio Oficial (USD) | E3: Entregables clave
A4: STANDARD | B4: 3 | C4: 197 | D4: 249 | E4: Indicador (3m); comunidad privada WhatsApp (señales); clases en vivo 1-2x/semana; todos los módulos de Skool
A5: PRO | B5: 6 | C5: 299 | D5: 397 | E5: Todo lo de STANDARD + indicador (6m) + señales VIP de altos ratios + soporte prioritario
A6: PREMIUM | B6: 12 | C6: 699 | D6: 799 | E6: Todo lo de PRO + indicador (12m) + Grupo Elite (mentoría 1 a 1)
A8: Nota: corte del precio de lanzamiento es por fecha fija (aún sin definir); política de renovación (precio oficial vs. de adquisición) pendiente. Ver pricing_strategy.md sección 3.

Sheet Embudo Trial
A1: Embudo de Adquisición — Free Trial
A3: Elemento | B3: Detalle
A4: Duración | B4: 15 días de acceso gratuito al indicador
A5: Incentivo económico | B5: Bono de $30 USD otorgado por el BROKER al registrarse (no es costo de Synapse)
A6: Educación | B6: Acceso al Módulo 1 de Skool (Trading básico)
A7: Comunidad | B7: Grupo abierto de WhatsApp: clases gratuitas + testimonios/casos de éxito diarios

Sheet Comisiones Embajadores
A1: Estructura de Comisión de Embajadores
A3: Evento | B3: Tasa de comisión
A4: Primera venta de un cliente referido | B4: 0.5
A5: Segunda re-compra en adelante (re-consumo) | B5: 0.25
A7: Ejemplo de comisión en USD por plan (vinculado a la pestaña Pricing)
A8: Plan | B8: Precio Lanzamiento | C8: Precio Oficial | D8: Comisión 1ra venta (lanz.) | E8: Comisión 1ra venta (of.) | F8: Comisión re-consumo (lanz.) | G8: Comisión re-consumo (of.)
A9: STANDARD | B9: ='Pricing'!C4 | C9: ='Pricing'!D4 | D9: =B9*$B$4 | E9: =C9*$B$4 | F9: =B9*$B$5 | G9: =C9*$B$5
A10: PRO | B10: ='Pricing'!C5 | C10: ='Pricing'!D5 | D10: =B10*$B$4 | E10: =C10*$B$4 | F10: =B10*$B$5 | G10: =C10*$B$5
A11: PREMIUM | B11: ='Pricing'!C6 | C11: ='Pricing'!D6 | D11: =B11*$B$4 | E11: =C11*$B$4 | F11: =B11*$B$5 | G11: =C11*$B$5

Sheet Escenarios Embajadores
A1: Matriz de Escenarios — Ingreso Anual de UN Embajador
A2: Fórmula: comisión_anual = n × P × [6 + 2.25r + 1.5r² + 0.75r³] (n=nuevos/mes, P=precio plan, r=retención trimestral)
A4: Precio Oficial STANDARD | F4: Precio usado: | G4: ='Pricing'!D4
A5: Volumen/mes (n) | B5: Conservador (20%) | C5: Base (40%) | D5: Optimista (60%)
A6: (r usado por columna →) | B6: 0.2 | C6: 0.4 | D6: 0.6
A7: Principiante (3/mes) | B7: =$H7*$G4*(6+2.25*B$6+1.5*B$6^2+0.75*B$6^3) | C7: =$H7*$G4*(6+2.25*C$6+1.5*C$6^2+0.75*C$6^3) | D7: =$H7*$G4*(6+2.25*D$6+1.5*D$6^2+0.75*D$6^3) | H7: 3
A8: Promedio (5/mes) | B8: =$H8*$G4*(6+2.25*B$6+1.5*B$6^2+0.75*B$6^3) | C8: =$H8*$G4*(6+2.25*C$6+1.5*C$6^2+0.75*C$6^3) | D8: =$H8*$G4*(6+2.25*D$6+1.5*D$6^2+0.75*D$6^3) | H8: 5
A9: Consistente (10/mes) | B9: =$H9*$G4*(6+2.25*B$6+1.5*B$6^2+0.75*B$6^3) | C9: =$H9*$G4*(6+2.25*C$6+1.5*C$6^2+0.75*C$6^3) | D9: =$H9*$G4*(6+2.25*D$6+1.5*D$6^2+0.75*D$6^3) | H9: 10
A10: Alto rendimiento (15/mes) | B10: =$H10*$G4*(6+2.25*B$6+1.5*B$6^2+0.75*B$6^3) | C10: =$H10*$G4*(6+2.25*C$6+1.5*C$6^2+0.75*C$6^3) | D10: =$H10*$G4*(6+2.25*D$6+1.5*D$6^2+0.75*D$6^3) | H10: 15
A11: Élite (20/mes) | B11: =$H11*$G4*(6+2.25*B$6+1.5*B$6^2+0.75*B$6^3) | C11: =$H11*$G4*(6+2.25*C$6+1.5*C$6^2+0.75*C$6^3) | D11: =$H11*$G4*(6+2.25*D$6+1.5*D$6^2+0.75*D$6^3) | H11: 20
A14: Precio Lanzamiento STANDARD | F14: Precio usado: | G14: ='Pricing'!C4
A15: Volumen/mes (n) | B15: Conservador (20%) | C15: Base (40%) | D15: Optimista (60%)
A16: (r usado por columna →) | B16: 0.2 | C16: 0.4 | D16: 0.6
A17: Principiante (3/mes) | B17: =$H17*$G14*(6+2.25*B$16+1.5*B$16^2+0.75*B$16^3) | C17: =$H17*$G14*(6+2.25*C$16+1.5*C$16^2+0.75*C$16^3) | D17: =$H17*$G14*(6+2.25*D$16+1.5*D$16^2+0.75*D$16^3) | H17: 3
A18: Promedio (5/mes) | B18: =$H18*$G14*(6+2.25*B$16+1.5*B$16^2+0.75*B$16^3) | C18: =$H18*$G14*(6+2.25*C$16+1.5*C$16^2+0.75*C$16^3) | D18: =$H18*$G14*(6+2.25*D$16+1.5*D$16^2+0.75*D$16^3) | H18: 5
A19: Consistente (10/mes) | B19: =$H19*$G14*(6+2.25*B$16+1.5*B$16^2+0.75*B$16^3) | C19: =$H19*$G14*(6+2.25*C$16+1.5*C$16^2+0.75*C$16^3) | D19: =$H19*$G14*(6+2.25*D$16+1.5*D$16^2+0.75*D$16^3) | H19: 10
A20: Alto rendimiento (15/mes) | B20: =$H20*$G14*(6+2.25*B$16+1.5*B$16^2+0.75*B$16^3) | C20: =$H20*$G14*(6+2.25*C$16+1.5*C$16^2+0.75*C$16^3) | D20: =$H20*$G14*(6+2.25*D$16+1.5*D$16^2+0.75*D$16^3) | H20: 15
A21: Élite (20/mes) | B21: =$H21*$G14*(6+2.25*B$16+1.5*B$16^2+0.75*B$16^3) | C21: =$H21*$G14*(6+2.25*C$16+1.5*C$16^2+0.75*C$16^3) | D21: =$H21*$G14*(6+2.25*D$16+1.5*D$16^2+0.75*D$16^3) | H21: 20

Sheet Modelo Financiero
A1: Modelo Financiero — Costos y Margen
A3: Costos fijos mensuales del negocio (confirmados 2026-07-07)
A4: Herramienta | B4: Costo mensual (USD)
A5: TradingView Premium | B5: 85
A6: Make (automatizaciones) | B6: 10
A7: Manychat | B7: 25
A8: Skool | B8: 10
A9: Claude | B9: 20
A10: Total costo_fijo_mensual_negocio | B10: =SUM(B5:B9)
A12: Costos aún sin confirmar (no inventar — dejar en 0 hasta tener el dato real)
A13: Variable | B13: Qué representa | C13: Valor
A14: fee_pago | B14: % de comisión de la pasarela de pago (Stripe, etc.) | C14: 0
A15: costo_soporte_mensual | B15: Costo de soporte/comunidad por cliente activo al mes | C15: 0
A16: costo_herramientas_mensual_por_cliente | B16: Prorrateo por cliente de alguna herramienta que escale con clientes | C16: 0
A19: Margen por venta individual (referido por embajador, primera venta, plan STANDARD, precio oficial)
A20: Precio del plan | B20: ='Pricing'!D4
A21: Ingreso neto de pago | B21: =B20*(1-C14)
A22: Comisión embajador (1ra venta, 50%) | B22: =B20*0.5
A23: Costo operativo del plan (soporte+herramientas × 3 meses) | B23: =(C15+C16)*3
A24: Margen neto | B24: =B21-B22-B23

Sheet Reparto Socios
A1: Reparto de Ganancia Libre
A3: Ganancia libre anual (input manual — pendiente de cifra real confirmada; costos de fee de pago y soporte de Modelo Financiero aún no están incluidos en ningún número real)
A4: Ganancia libre anual (USD) | B4: 0
A6: Destino | B6: % de la ganancia libre | C6: Monto (USD)
A7: Gustavo (estratega digital) | B7: 0.25 | C7: =$B$4*B7
A8: Reserva (impuestos/imprevistos/stack de plataformas) | B8: 0.15 | C8: =$B$4*B8
A9: Fundador | B9: 0.3 | C9: =$B$4*B9
A10: Meli (rol comercial) | B10: 0.3 | C10: =$B$4*B10
A11: Total | B11: =SUM(B7:B10) | C11: =SUM(C7:C10)
A14: Ejemplo ilustrativo ya calculado en la conversación (escenario: 10 embajadores × 10 nuevos/mes, 40% retención trimestral, STANDARD) — NO es una cifra real medida
A15: Escenario | B15: Ganancia libre anual estimada
A16: Precio de lanzamiento | B16: 186610.8
A17: Precio oficial | B17: 238143.6
